docling_ibm_models/__init__.py
docling_ibm_models/py.typed
docling_ibm_models/code_formula_model/__init__.py
docling_ibm_models/code_formula_model/code_formula_predictor.py
docling_ibm_models/code_formula_model/models/__init__.py
docling_ibm_models/code_formula_model/models/sam.py
docling_ibm_models/code_formula_model/models/sam_opt.py
docling_ibm_models/code_formula_model/models/sam_opt_image_processor.py
docling_ibm_models/document_figure_classifier_model/__init__.py
docling_ibm_models/document_figure_classifier_model/document_figure_classifier_predictor.py
docling_ibm_models/layoutmodel/__init__.py
docling_ibm_models/layoutmodel/labels.py
docling_ibm_models/layoutmodel/layout_predictor.py
docling_ibm_models/list_item_normalizer/__init__.py
docling_ibm_models/list_item_normalizer/list_marker_processor.py
docling_ibm_models/reading_order/__init__.py
docling_ibm_models/reading_order/reading_order_rb.py
docling_ibm_models/tableformer/__init__.py
docling_ibm_models/tableformer/common.py
docling_ibm_models/tableformer/otsl.py
docling_ibm_models/tableformer/settings.py
docling_ibm_models/tableformer/data_management/__init__.py
docling_ibm_models/tableformer/data_management/functional.py
docling_ibm_models/tableformer/data_management/matching_post_processor.py
docling_ibm_models/tableformer/data_management/tf_cell_matcher.py
docling_ibm_models/tableformer/data_management/tf_predictor.py
docling_ibm_models/tableformer/data_management/transforms.py
docling_ibm_models/tableformer/models/__init__.py
docling_ibm_models/tableformer/models/common/__init__.py
docling_ibm_models/tableformer/models/common/base_model.py
docling_ibm_models/tableformer/models/table04_rs/__init__.py
docling_ibm_models/tableformer/models/table04_rs/bbox_decoder_rs.py
docling_ibm_models/tableformer/models/table04_rs/encoder04_rs.py
docling_ibm_models/tableformer/models/table04_rs/tablemodel04_rs.py
docling_ibm_models/tableformer/models/table04_rs/transformer_rs.py
docling_ibm_models-3.10.1.dist-info/licenses/LICENSE
docling_ibm_models-3.10.1.dist-info/METADATA
docling_ibm_models-3.10.1.dist-info/WHEEL
docling_ibm_models-3.10.1.dist-info/top_level.txt
docling_ibm_models-3.10.1.dist-info/RECORD
