Metadata-Version: 2.4
Name: docling-ibm-models
Version: 3.10.1
Summary: This package contains the AI models used by the Docling PDF conversion package
Author-email: Nikos Livathinos <nli@zurich.ibm.com>, Maxim Lysak <mly@zurich.ibm.com>, Ahmed Nassar <ahn@zurich.ibm.com>, Christoph Auer <cau@zurich.ibm.com>, Michele Dolfi <dol@zurich.ibm.com>, Peter Staar <taa@zurich.ibm.com>
License-Expression: MIT
Project-URL: homepage, https://github.com/docling-project/docling-ibm-models
Project-URL: repository, https://github.com/docling-project/docling-ibm-models
Project-URL: issues, https://github.com/docling-project/docling-ibm-models/issues
Project-URL: changelog, https://github.com/docling-project/docling-ibm-models/blob/main/CHANGELOG.md
Keywords: docling,convert,document,pdf,layout model,segmentation,table structure,table former
Classifier: Operating System :: MacOS :: MacOS X
Classifier: Operating System :: POSIX :: Linux
Classifier: Operating System :: Microsoft :: Windows
Classifier: Development Status :: 5 - Production/Stable
Classifier: Intended Audience :: Developers
Classifier: Intended Audience :: Science/Research
Classifier: Topic :: Scientific/Engineering :: Artificial Intelligence
Classifier: Programming Language :: Python :: 3
Classifier: Programming Language :: Python :: 3.9
Classifier: Programming Language :: Python :: 3.10
Classifier: Programming Language :: Python :: 3.11
Classifier: Programming Language :: Python :: 3.12
Classifier: Programming Language :: Python :: 3.13
Classifier: Programming Language :: Python :: 3.14
Requires-Python: <4.0,>=3.9
License-File: LICENSE
Requires-Dist: torch<3.0.0,>=2.2.2
Requires-Dist: torchvision<1,>=0
Requires-Dist: jsonlines<5.0.0,>=3.1.0
Requires-Dist: Pillow<13.0.0,>=10.0.0
Requires-Dist: tqdm<5.0.0,>=4.64.0
Requires-Dist: huggingface_hub<1,>=0.23
Requires-Dist: safetensors[torch]<1,>=0.4.3
Requires-Dist: pydantic<3.0.0,>=2.0.0
Requires-Dist: docling-core<3.0.0,>=2.19.0
Requires-Dist: transformers<5.0.0,>=4.42.0
Requires-Dist: numpy<3.0.0,>=1.24.4
Requires-Dist: rtree>=1.0.0
Requires-Dist: accelerate<2.0.0,>=1.2.1
Provides-Extra: opencv-python-headless
Requires-Dist: opencv-python-headless<5.0.0.0,>=4.6.0.66; extra == "opencv-python-headless"
Provides-Extra: opencv-python
Requires-Dist: opencv-python<5.0.0.0,>=4.6.0.66; extra == "opencv-python"
Dynamic: license-file
